LICENSE
README.md
setup.py
nldk/__init__.py
nldk/all_languages.py
nldk/basic_object.py
nldk/cli_menu.py
nldk/load_nltk.py
nldk/nlp_content_cleaner.py
nldk/print_file_lines.py
nldk/tmx.py
nldk/tmx2csv.py
nldk/tsv2csv.py
nldk/write_csv_line.py
nldk.egg-info/PKG-INFO
nldk.egg-info/SOURCES.txt
nldk.egg-info/dependency_links.txt
nldk.egg-info/requires.txt
nldk.egg-info/top_level.txt
nldk/bin/nldk